potcoder-1.2.4.dist-info/METADATA
potcoder-1.2.4.dist-info/WHEEL
potcoder-1.2.4.dist-info/licenses/LICENSE
potcoder/.env
potcoder/__init__.py
potcoder/assets/potcoder-screenshot.png
potcoder-1.2.4.dist-info/RECORD
