Metadata-Version: 2.1
Name: potcoder
Version: 1.2.4
Summary: A module created for the Python language that makes programming easier for programmers and developers
Author-Email: Thai Minh Nguyen <nguyenthaiminh0973200965@gmail.com>
Classifier: Programming Language :: Python :: 3
Classifier: License :: OSI Approved :: MIT License
Classifier: Operating System :: OS Independent
Project-URL: Homepage, https://github.com/hiactions/potcoder
Project-URL: Issues, https://github.com/hiactions/potcoder/issues
Requires-Python: >=3.8
